abdoTheBest/Document.py
abdoTheBest/__init__.py
abdoTheBest/controllers.py
abdoTheBest/embedding.py
abdoTheBest/generator.py
abdoTheBest/gpt2.py
abdoTheBest/gpt2_summarizer.py
abdoTheBest/gru.py
abdoTheBest/importers.py
abdoTheBest/lstm.py
abdoTheBest/preprocessing.py
abdoTheBest-1.0.0.dist-info/LICENSE.txt
abdoTheBest-1.0.0.dist-info/METADATA
abdoTheBest-1.0.0.dist-info/WHEEL
abdoTheBest-1.0.0.dist-info/top_level.txt
abdoTheBest-1.0.0.dist-info/RECORD
