Metadata-Version: 2.1
Name: abdoTheBest
Version: 1.0.0
Summary: A small example package
Home-page: https://github.com/gituser/example-pkg
Author: Fahed Sabellioglu, Abdelrahman Mahmoud
Author-email: abdohossan@gmail.com, sabellioglu@gmail.com
License: MIT
Platform: UNKNOWN
Requires-Python: >=3.0
License-File: LICENSE.txt
